botocore-stubs/__init__.pyi
botocore-stubs/args.pyi
botocore-stubs/auth.pyi
botocore-stubs/awsrequest.pyi
botocore-stubs/client.pyi
botocore-stubs/compat.pyi
botocore-stubs/compress.pyi
botocore-stubs/config.pyi
botocore-stubs/configloader.pyi
botocore-stubs/configprovider.pyi
botocore-stubs/context.pyi
botocore-stubs/credentials.pyi
botocore-stubs/discovery.pyi
botocore-stubs/endpoint.pyi
botocore-stubs/endpoint_provider.pyi
botocore-stubs/errorfactory.pyi
botocore-stubs/eventstream.pyi
botocore-stubs/exceptions.pyi
botocore-stubs/handlers.pyi
botocore-stubs/history.pyi
botocore-stubs/hooks.pyi
botocore-stubs/httpchecksum.pyi
botocore-stubs/httpsession.pyi
botocore-stubs/loaders.pyi
botocore-stubs/model.pyi
botocore-stubs/monitoring.pyi
botocore-stubs/paginate.pyi
botocore-stubs/parsers.pyi
botocore-stubs/plugin.pyi
botocore-stubs/py.typed
botocore-stubs/regions.pyi
botocore-stubs/response.pyi
botocore-stubs/retryhandler.pyi
botocore-stubs/serialize.pyi
botocore-stubs/session.pyi
botocore-stubs/signers.pyi
botocore-stubs/stub.pyi
botocore-stubs/tokens.pyi
botocore-stubs/translate.pyi
botocore-stubs/useragent.pyi
botocore-stubs/utils.pyi
botocore-stubs/validate.pyi
botocore-stubs/waiter.pyi
botocore-stubs/crt/__init__.pyi
botocore-stubs/crt/auth.pyi
botocore-stubs/docs/__init__.pyi
botocore-stubs/docs/client.pyi
botocore-stubs/docs/docstring.pyi
botocore-stubs/docs/example.pyi
botocore-stubs/docs/method.pyi
botocore-stubs/docs/paginator.pyi
botocore-stubs/docs/params.pyi
botocore-stubs/docs/service.pyi
botocore-stubs/docs/shape.pyi
botocore-stubs/docs/sharedexample.pyi
botocore-stubs/docs/translator.pyi
botocore-stubs/docs/utils.pyi
botocore-stubs/docs/waiter.pyi
botocore-stubs/docs/bcdoc/__init__.pyi
botocore-stubs/docs/bcdoc/docstringparser.pyi
botocore-stubs/docs/bcdoc/restdoc.pyi
botocore-stubs/docs/bcdoc/style.pyi
botocore-stubs/retries/__init__.pyi
botocore-stubs/retries/adaptive.pyi
botocore-stubs/retries/base.pyi
botocore-stubs/retries/bucket.pyi
botocore_stubs-1.42.39.dist-info/licenses/LICENSE
botocore_stubs-1.42.39.dist-info/METADATA
botocore_stubs-1.42.39.dist-info/WHEEL
botocore_stubs-1.42.39.dist-info/top_level.txt
botocore_stubs-1.42.39.dist-info/RECORD
