Metadata-Version: 2.4
Name: botocore-stubs
Version: 1.42.39
Summary: Type annotations and code completion for botocore
Author-email: Vlad Emelianov <vlad.emelianov.nz@gmail.com>
License-Expression: MIT
Project-URL: Homepage, https://github.com/youtype/botocore-stubs
Project-URL: Documentation, https://youtype.github.io/mypy_boto3_builder/
Project-URL: Repository, https://github.com/youtype/botocore-stubs
Project-URL: Changelog, https://github.com/youtype/botocore-stubs/releases
Project-URL: Issues, https://github.com/youtype/botocore-stubs/issues
Keywords: botocore,type-annotations,pyright,mypy,boto3
Classifier: Development Status :: 5 - Production/Stable
Classifier: Environment :: Console
Classifier: Natural Language :: English
Classifier: Operating System :: OS Independent
Classifier: Programming Language :: Python :: 3
Classifier: Programming Language :: Python :: 3.9
Classifier: Programming Language :: Python :: 3.10
Classifier: Programming Language :: Python :: 3.11
Classifier: Programming Language :: Python :: 3.12
Classifier: Programming Language :: Python :: 3.13
Classifier: Programming Language :: Python :: 3.14
Classifier: Programming Language :: Python :: 3 :: Only
Classifier: Programming Language :: Python :: Implementation :: CPython
Classifier: Typing :: Stubs Only
Classifier: Topic :: Software Development :: Libraries :: Python Modules
Requires-Python: >=3.9
License-File: LICENSE
Requires-Dist: types-awscrt
Provides-Extra: botocore
Requires-Dist: botocore; extra == "botocore"
Dynamic: license-file
